<?xml version="1.0" encoding="US-ASCII" standalone="yes"?><?mso-application progid="Excel.Sheet"?><Workbook xmlns="urn:schemas-microsoft-com:office:spreadsheet" xmlns:o="urn:schemas-microsoft-com:office:office" xmlns:x="urn:schemas-microsoft-com:office:excel" xmlns:ss="urn:schemas-microsoft-com:office:spreadsheet" xmlns:html="http://www.w3.org/TR/REC-html40"><DocumentProperties xmlns="urn:schemas-microsoft-com:office:office"><Author></Author><LastAuthor></LastAuthor><Created></Created><LastSaved></LastSaved><Company></Company><Version></Version></DocumentProperties><ExcelWorkbook  xmlns="urn:schemas-microsoft-com:office:excel"><ProtectStructure>False</ProtectStructure><ProtectWindows>False</ProtectWindows></ExcelWorkbook><Styles><Style ss:ID="Default" ss:Name="Normal"><Alignment ss:Vertical="Bottom"/><Borders/><Font ss:FontName="Calibri" ss:Size="10"/><Interior/><NumberFormat/><Protection/></Style><Style ss:ID="s1"><Font ss:FontName="Calibri" ss:Bold="1" ss:Size="12"/><NumberFormat/></Style><Style ss:ID="s21"><Alignment ss:Horizontal="Center" ss:Vertical="Bottom"/><NumberFormat/><Font ss:FontName="Calibri" ss:Size="10"/><Borders><Border ss:Position="Top" ss:LineStyle="Continuous" ss:Weight="1"/></Borders></Style><Style ss:ID="s22"><Alignment ss:Horizontal="Center" ss:Vertical="Bottom"/><Font ss:FontName="Calibri" ss:Size="10"/><NumberFormat/></Style><Style ss:ID="s23"><Alignment ss:Horizontal="Center" ss:Vertical="Bottom"/><NumberFormat/><Font ss:FontName="Calibri" ss:Size="10"/><Borders><Border ss:Position="Bottom" ss:LineStyle="Continuous" ss:Weight="1"/></Borders></Style><Style ss:ID="s24"><Font ss:FontName="Calibri" ss:Size="10"/><NumberFormat/></Style><Style ss:ID="s31"><Font ss:FontName="Calibri" ss:Size="10"/><Borders><Border ss:Position="Top" ss:LineStyle="Continuous" ss:Weight="1"/></Borders></Style><Style ss:ID="s32"><Font ss:FontName="Calibri" ss:Size="10"/><Borders/></Style><Style ss:ID="s33"><Font ss:FontName="Calibri" ss:Size="10"/><Borders><Border ss:Position="Bottom" ss:LineStyle="Continuous" ss:Weight="1"/></Borders></Style></Styles><Names></Names><Worksheet ss:Name="Sheet1"><Table ss:ExpandedColumnCount="6" ss:ExpandedRowCount="34" x:FullColumns="1" x:FullRows="1"><Column ss:AutoFitWidth="0" ss:Width="220"/><Column ss:AutoFitWidth="0" ss:Width="58"/><Column ss:AutoFitWidth="0" ss:Width="58"/><Column ss:AutoFitWidth="0" ss:Width="58"/><Column ss:AutoFitWidth="0" ss:Width="58"/><Column ss:AutoFitWidth="0" ss:Width="58"/><Row></Row><Row><Cell ss:StyleID="s1"><Data ss:Type="String">Table X: Catch_X_Sold (nd_score)</Data></Cell></Row><Row><Cell ss:StyleID="s31"><Data ss:Type="String"></Data></Cell><Cell ss:StyleID="s21"><Data ss:Type="String">(1)</Data></Cell><Cell ss:StyleID="s21"><Data ss:Type="String">(2)</Data></Cell><Cell ss:StyleID="s21"><Data ss:Type="String">(3)</Data></Cell><Cell ss:StyleID="s21"><Data ss:Type="String">(4)</Data></Cell><Cell ss:StyleID="s21"><Data ss:Type="String">(5)</Data></Cell></Row><Row><Cell ss:StyleID="s32"><Data ss:Type="String"></Data></Cell><Cell ss:StyleID="s22"><Data ss:Type="String">base</Data></Cell><Cell ss:StyleID="s22"><Data ss:Type="String">effort</Data></Cell><Cell ss:StyleID="s22"><Data ss:Type="String">hh</Data></Cell><Cell ss:StyleID="s22"><Data ss:Type="String">mkt</Data></Cell><Cell ss:StyleID="s22"><Data ss:Type="String">mktx</Data></Cell></Row><Row><Cell ss:StyleID="s32"><Data ss:Type="String">VARIABLES</Data></Cell><Cell ss:StyleID="s22"><Data ss:Type="String">Nutrient density score: sold level</Data></Cell><Cell ss:StyleID="s22"><Data ss:Type="String">Nutrient density score: sold level</Data></Cell><Cell ss:StyleID="s22"><Data ss:Type="String">Nutrient density score: sold level</Data></Cell><Cell ss:StyleID="s22"><Data ss:Type="String">Nutrient density score: sold level</Data></Cell><Cell ss:StyleID="s22"><Data ss:Type="String">Nutrient density score: sold level</Data></Cell></Row><Row><Cell ss:StyleID="s31"><Data ss:Type="String"></Data></Cell><Cell ss:StyleID="s21"><Data ss:Type="String"></Data></Cell><Cell ss:StyleID="s21"><Data ss:Type="String"></Data></Cell><Cell ss:StyleID="s21"><Data ss:Type="String"></Data></Cell><Cell ss:StyleID="s21"><Data ss:Type="String"></Data></Cell><Cell ss:StyleID="s21"><Data ss:Type="String"></Data></Cell></Row><Row><Cell ss:StyleID="s32"><Data ss:Type="String">Nutrient density score: catch level</Data></Cell><Cell ss:StyleID="s22"><Data ss:Type="String">0.672***</Data></Cell><Cell ss:StyleID="s22"><Data ss:Type="String">0.488**</Data></Cell><Cell ss:StyleID="s22"><Data ss:Type="String">0.487**</Data></Cell><Cell ss:StyleID="s22"><Data ss:Type="String">0.516**</Data></Cell><Cell ss:StyleID="s22"><Data ss:Type="String">0.715</Data></Cell></Row><Row><Cell ss:StyleID="s32"><Data ss:Type="String"></Data></Cell><Cell ss:StyleID="s22"><Data ss:Type="String">(0.226)</Data></Cell><Cell ss:StyleID="s22"><Data ss:Type="String">(0.221)</Data></Cell><Cell ss:StyleID="s22"><Data ss:Type="String">(0.199)</Data></Cell><Cell ss:StyleID="s22"><Data ss:Type="String">(0.199)</Data></Cell><Cell ss:StyleID="s22"><Data ss:Type="String">(0.495)</Data></Cell></Row><Row><Cell ss:StyleID="s32"><Data ss:Type="String">Distance to nearest large town (km)--Battambang, Kampong Thom, Pursat, Siem Reap</Data></Cell><Cell ss:StyleID="s22"><Data ss:Type="String"></Data></Cell><Cell ss:StyleID="s22"><Data ss:Type="String"></Data></Cell><Cell ss:StyleID="s22"><Data ss:Type="String"></Data></Cell><Cell ss:StyleID="s22"><Data ss:Type="String">-0.00728</Data></Cell><Cell ss:StyleID="s22"><Data ss:Type="String">0.0158</Data></Cell></Row><Row><Cell ss:StyleID="s32"><Data ss:Type="String"></Data></Cell><Cell ss:StyleID="s22"><Data ss:Type="String"></Data></Cell><Cell ss:StyleID="s22"><Data ss:Type="String"></Data></Cell><Cell ss:StyleID="s22"><Data ss:Type="String"></Data></Cell><Cell ss:StyleID="s22"><Data ss:Type="String">(0.00509)</Data></Cell><Cell ss:StyleID="s22"><Data ss:Type="String">(0.0478)</Data></Cell></Row><Row><Cell ss:StyleID="s32"><Data ss:Type="String">c.nd_score_catch#c.city_distance</Data></Cell><Cell ss:StyleID="s22"><Data ss:Type="String"></Data></Cell><Cell ss:StyleID="s22"><Data ss:Type="String"></Data></Cell><Cell ss:StyleID="s22"><Data ss:Type="String"></Data></Cell><Cell ss:StyleID="s22"><Data ss:Type="String"></Data></Cell><Cell ss:StyleID="s22"><Data ss:Type="String">-0.00589</Data></Cell></Row><Row><Cell ss:StyleID="s32"><Data ss:Type="String"></Data></Cell><Cell ss:StyleID="s22"><Data ss:Type="String"></Data></Cell><Cell ss:StyleID="s22"><Data ss:Type="String"></Data></Cell><Cell ss:StyleID="s22"><Data ss:Type="String"></Data></Cell><Cell ss:StyleID="s22"><Data ss:Type="String"></Data></Cell><Cell ss:StyleID="s22"><Data ss:Type="String">(0.0124)</Data></Cell></Row><Row><Cell ss:StyleID="s32"><Data ss:Type="String">Person-days</Data></Cell><Cell ss:StyleID="s22"><Data ss:Type="String"></Data></Cell><Cell ss:StyleID="s22"><Data ss:Type="String">0.0379***</Data></Cell><Cell ss:StyleID="s22"><Data ss:Type="String">0.0401***</Data></Cell><Cell ss:StyleID="s22"><Data ss:Type="String">0.0415***</Data></Cell><Cell ss:StyleID="s22"><Data ss:Type="String">0.0415***</Data></Cell></Row><Row><Cell ss:StyleID="s32"><Data ss:Type="String"></Data></Cell><Cell ss:StyleID="s22"><Data ss:Type="String"></Data></Cell><Cell ss:StyleID="s22"><Data ss:Type="String">(0.00619)</Data></Cell><Cell ss:StyleID="s22"><Data ss:Type="String">(0.00591)</Data></Cell><Cell ss:StyleID="s22"><Data ss:Type="String">(0.00568)</Data></Cell><Cell ss:StyleID="s22"><Data ss:Type="String">(0.00564)</Data></Cell></Row><Row><Cell ss:StyleID="s32"><Data ss:Type="String">Effort-squared</Data></Cell><Cell ss:StyleID="s22"><Data ss:Type="String"></Data></Cell><Cell ss:StyleID="s22"><Data ss:Type="String">-0.000125***</Data></Cell><Cell ss:StyleID="s22"><Data ss:Type="String">-0.000129***</Data></Cell><Cell ss:StyleID="s22"><Data ss:Type="String">-0.000136***</Data></Cell><Cell ss:StyleID="s22"><Data ss:Type="String">-0.000136***</Data></Cell></Row><Row><Cell ss:StyleID="s32"><Data ss:Type="String"></Data></Cell><Cell ss:StyleID="s22"><Data ss:Type="String"></Data></Cell><Cell ss:StyleID="s22"><Data ss:Type="String">(3.09e-05)</Data></Cell><Cell ss:StyleID="s22"><Data ss:Type="String">(2.82e-05)</Data></Cell><Cell ss:StyleID="s22"><Data ss:Type="String">(2.74e-05)</Data></Cell><Cell ss:StyleID="s22"><Data ss:Type="String">(2.72e-05)</Data></Cell></Row><Row><Cell ss:StyleID="s32"><Data ss:Type="String">Household size</Data></Cell><Cell ss:StyleID="s22"><Data ss:Type="String"></Data></Cell><Cell ss:StyleID="s22"><Data ss:Type="String"></Data></Cell><Cell ss:StyleID="s22"><Data ss:Type="String">-0.0576</Data></Cell><Cell ss:StyleID="s22"><Data ss:Type="String">-0.0604</Data></Cell><Cell ss:StyleID="s22"><Data ss:Type="String">-0.0637</Data></Cell></Row><Row><Cell ss:StyleID="s32"><Data ss:Type="String"></Data></Cell><Cell ss:StyleID="s22"><Data ss:Type="String"></Data></Cell><Cell ss:StyleID="s22"><Data ss:Type="String"></Data></Cell><Cell ss:StyleID="s22"><Data ss:Type="String">(0.0590)</Data></Cell><Cell ss:StyleID="s22"><Data ss:Type="String">(0.0579)</Data></Cell><Cell ss:StyleID="s22"><Data ss:Type="String">(0.0590)</Data></Cell></Row><Row><Cell ss:StyleID="s32"><Data ss:Type="String">Share of household members &lt;=15 or &gt;=65</Data></Cell><Cell ss:StyleID="s22"><Data ss:Type="String"></Data></Cell><Cell ss:StyleID="s22"><Data ss:Type="String"></Data></Cell><Cell ss:StyleID="s22"><Data ss:Type="String">1.367</Data></Cell><Cell ss:StyleID="s22"><Data ss:Type="String">1.313</Data></Cell><Cell ss:StyleID="s22"><Data ss:Type="String">1.300</Data></Cell></Row><Row><Cell ss:StyleID="s32"><Data ss:Type="String"></Data></Cell><Cell ss:StyleID="s22"><Data ss:Type="String"></Data></Cell><Cell ss:StyleID="s22"><Data ss:Type="String"></Data></Cell><Cell ss:StyleID="s22"><Data ss:Type="String">(1.274)</Data></Cell><Cell ss:StyleID="s22"><Data ss:Type="String">(1.259)</Data></Cell><Cell ss:StyleID="s22"><Data ss:Type="String">(1.266)</Data></Cell></Row><Row><Cell ss:StyleID="s32"><Data ss:Type="String">Max educational attainment by any hh member (years)</Data></Cell><Cell ss:StyleID="s22"><Data ss:Type="String"></Data></Cell><Cell ss:StyleID="s22"><Data ss:Type="String"></Data></Cell><Cell ss:StyleID="s22"><Data ss:Type="String">0.0150</Data></Cell><Cell ss:StyleID="s22"><Data ss:Type="String">0.0149</Data></Cell><Cell ss:StyleID="s22"><Data ss:Type="String">0.0151</Data></Cell></Row><Row><Cell ss:StyleID="s32"><Data ss:Type="String"></Data></Cell><Cell ss:StyleID="s22"><Data ss:Type="String"></Data></Cell><Cell ss:StyleID="s22"><Data ss:Type="String"></Data></Cell><Cell ss:StyleID="s22"><Data ss:Type="String">(0.0244)</Data></Cell><Cell ss:StyleID="s22"><Data ss:Type="String">(0.0242)</Data></Cell><Cell ss:StyleID="s22"><Data ss:Type="String">(0.0240)</Data></Cell></Row><Row><Cell ss:StyleID="s32"><Data ss:Type="String">Household amenities index</Data></Cell><Cell ss:StyleID="s22"><Data ss:Type="String"></Data></Cell><Cell ss:StyleID="s22"><Data ss:Type="String"></Data></Cell><Cell ss:StyleID="s22"><Data ss:Type="String">0.0907</Data></Cell><Cell ss:StyleID="s22"><Data ss:Type="String">0.0775</Data></Cell><Cell ss:StyleID="s22"><Data ss:Type="String">0.0767</Data></Cell></Row><Row><Cell ss:StyleID="s32"><Data ss:Type="String"></Data></Cell><Cell ss:StyleID="s22"><Data ss:Type="String"></Data></Cell><Cell ss:StyleID="s22"><Data ss:Type="String"></Data></Cell><Cell ss:StyleID="s22"><Data ss:Type="String">(0.107)</Data></Cell><Cell ss:StyleID="s22"><Data ss:Type="String">(0.106)</Data></Cell><Cell ss:StyleID="s22"><Data ss:Type="String">(0.106)</Data></Cell></Row><Row><Cell ss:StyleID="s32"><Data ss:Type="String">Livelihood asset index</Data></Cell><Cell ss:StyleID="s22"><Data ss:Type="String"></Data></Cell><Cell ss:StyleID="s22"><Data ss:Type="String"></Data></Cell><Cell ss:StyleID="s22"><Data ss:Type="String">0.107*</Data></Cell><Cell ss:StyleID="s22"><Data ss:Type="String">0.0924</Data></Cell><Cell ss:StyleID="s22"><Data ss:Type="String">0.0906</Data></Cell></Row><Row><Cell ss:StyleID="s32"><Data ss:Type="String"></Data></Cell><Cell ss:StyleID="s22"><Data ss:Type="String"></Data></Cell><Cell ss:StyleID="s22"><Data ss:Type="String"></Data></Cell><Cell ss:StyleID="s22"><Data ss:Type="String">(0.0608)</Data></Cell><Cell ss:StyleID="s22"><Data ss:Type="String">(0.0603)</Data></Cell><Cell ss:StyleID="s22"><Data ss:Type="String">(0.0595)</Data></Cell></Row><Row><Cell ss:StyleID="s32"><Data ss:Type="String">Constant</Data></Cell><Cell ss:StyleID="s22"><Data ss:Type="String">-0.338</Data></Cell><Cell ss:StyleID="s22"><Data ss:Type="String">-1.341*</Data></Cell><Cell ss:StyleID="s22"><Data ss:Type="String">-1.432</Data></Cell><Cell ss:StyleID="s22"><Data ss:Type="String">-1.300</Data></Cell><Cell ss:StyleID="s22"><Data ss:Type="String">-2.058</Data></Cell></Row><Row><Cell ss:StyleID="s32"><Data ss:Type="String"></Data></Cell><Cell ss:StyleID="s22"><Data ss:Type="String">(0.847)</Data></Cell><Cell ss:StyleID="s22"><Data ss:Type="String">(0.787)</Data></Cell><Cell ss:StyleID="s22"><Data ss:Type="String">(0.928)</Data></Cell><Cell ss:StyleID="s22"><Data ss:Type="String">(0.890)</Data></Cell><Cell ss:StyleID="s22"><Data ss:Type="String">(1.861)</Data></Cell></Row><Row><Cell ss:StyleID="s32"><Data ss:Type="String"></Data></Cell><Cell ss:StyleID="s22"><Data ss:Type="String"></Data></Cell><Cell ss:StyleID="s22"><Data ss:Type="String"></Data></Cell><Cell ss:StyleID="s22"><Data ss:Type="String"></Data></Cell><Cell ss:StyleID="s22"><Data ss:Type="String"></Data></Cell><Cell ss:StyleID="s22"><Data ss:Type="String"></Data></Cell></Row><Row><Cell ss:StyleID="s32"><Data ss:Type="String">Observations</Data></Cell><Cell ss:StyleID="s22"><Data ss:Type="String">410</Data></Cell><Cell ss:StyleID="s22"><Data ss:Type="String">410</Data></Cell><Cell ss:StyleID="s22"><Data ss:Type="String">410</Data></Cell><Cell ss:StyleID="s22"><Data ss:Type="String">410</Data></Cell><Cell ss:StyleID="s22"><Data ss:Type="String">410</Data></Cell></Row><Row><Cell ss:StyleID="s33"><Data ss:Type="String">R-squared</Data></Cell><Cell ss:StyleID="s23"><Data ss:Type="String">0.034</Data></Cell><Cell ss:StyleID="s23"><Data ss:Type="String">0.165</Data></Cell><Cell ss:StyleID="s23"><Data ss:Type="String">0.190</Data></Cell><Cell ss:StyleID="s23"><Data ss:Type="String">0.195</Data></Cell><Cell ss:StyleID="s23"><Data ss:Type="String">0.196</Data></Cell></Row><Row><Cell ss:StyleID="s24"><Data ss:Type="String">Robust standard errors in parentheses</Data></Cell></Row><Row><Cell ss:StyleID="s24"><Data ss:Type="String">*** p&lt;0.01, ** p&lt;0.05, * p&lt;0.1</Data></Cell></Row><Row><Cell ss:StyleID="s24"><Data ss:Type="String">Outcome variable is nd_score at the catch level. Robust standard errors clustered at CFR level in parentheses. *** p&lt;0.01, ** p&lt;0.05, * p&lt;0.1</Data></Cell></Row></Table><WorksheetOptions xmlns="urn:schemas-microsoft-com:office:excel"><ProtectedObjects>False</ProtectedObjects><ProtectedScenarios>False</ProtectedScenarios></WorksheetOptions></Worksheet></Workbook>